mcp_interviewer/__init__.py
mcp_interviewer/__main__.py
mcp_interviewer/_version.py
mcp_interviewer/cli.py
mcp_interviewer/main.py
mcp_interviewer/models.py
mcp_interviewer/constraints/__init__.py
mcp_interviewer/constraints/base.py
mcp_interviewer/constraints/openai.py
mcp_interviewer/constraints/tool_schema_flatness.py
mcp_interviewer/interviewer/__init__.py
mcp_interviewer/interviewer/_interviewer.py
mcp_interviewer/interviewer/callbacks.py
mcp_interviewer/interviewer/connection.py
mcp_interviewer/interviewer/inspection.py
mcp_interviewer/interviewer/test_execution.py
mcp_interviewer/interviewer/test_generation.py
mcp_interviewer/interviewer/test_judging.py
mcp_interviewer/interviewer/tool_judging.py
mcp_interviewer/prompts/__init__.py
mcp_interviewer/prompts/_generate_functional_test.py
mcp_interviewer/prompts/_score_functional_test_output.py
mcp_interviewer/prompts/_score_functional_test_step_output.py
mcp_interviewer/prompts/_score_tool.py
mcp_interviewer/prompts/utils.py
mcp_interviewer/reports/__init__.py
mcp_interviewer/reports/base.py
mcp_interviewer/reports/custom.py
mcp_interviewer/reports/full.py
mcp_interviewer/reports/utils.py
mcp_interviewer/reports/functional_test/__init__.py
mcp_interviewer/reports/functional_test/failed_tests.py
mcp_interviewer/reports/functional_test/score_summary.py
mcp_interviewer/reports/functional_test/test.py
mcp_interviewer/reports/functional_test/test_step.py
mcp_interviewer/reports/functional_test/tool_scorecards.py
mcp_interviewer/reports/interviewer/__init__.py
mcp_interviewer/reports/interviewer/constraint_violations.py
mcp_interviewer/reports/interviewer/emoji_legend.py
mcp_interviewer/reports/interviewer/interviewer_info.py
mcp_interviewer/reports/interviewer/model_info.py
mcp_interviewer/reports/server/__init__.py
mcp_interviewer/reports/server/capabilities.py
mcp_interviewer/reports/server/prompts.py
mcp_interviewer/reports/server/resource_templates.py
mcp_interviewer/reports/server/resources.py
mcp_interviewer-0.0.12.dist-info/METADATA
mcp_interviewer-0.0.12.dist-info/WHEEL
mcp_interviewer-0.0.12.dist-info/entry_points.txt
mcp_interviewer-0.0.12.dist-info/licenses/LICENSE
mcp_interviewer-0.0.12.dist-info/RECORD
