Metadata-Version: 2.4
Name: mcp-interviewer
Version: 0.0.12
Summary: A tool for analyzing and testing MCP (Model Context Protocol) servers and their tools
License-File: LICENSE
Requires-Python: >=3.11
Requires-Dist: jsonschema>=4.0.0
Requires-Dist: mcp>=1.10.1
Requires-Dist: openai>=1.93.3
Requires-Dist: tiktoken>=0.11.0
